pyfairdesk/__init__.py
pyfairdesk/private.py
pyfairdesk/public.py
pyfairdesk/rest_api.py
pyfairdesk/stream.py
pyfairdesk/stream_api.py
pyfairdesk-0.0.3.dist-info/LICENSE
pyfairdesk-0.0.3.dist-info/METADATA
pyfairdesk-0.0.3.dist-info/WHEEL
pyfairdesk-0.0.3.dist-info/top_level.txt
pyfairdesk-0.0.3.dist-info/RECORD
